crunchy_bot/__init__.py
crunchy_bot/client/__init__.py
crunchy_bot/client/cli.py
crunchy_bot/client/version.py
crunchy_bot/config/__init__.py
crunchy_bot/config/config_parser.py
crunchy_bot/config/json_config_parser.py
crunchy_bot/config/test_json_config_parser.py
crunchy_bot/fetcher/__init__.py
crunchy_bot/fetcher/fetcher.py
crunchy_bot/fetcher/guest_pass_fetcher.py
crunchy_bot/fetcher/test_guest_pass_fetcher.py
crunchy_bot/logging/__init__.py
crunchy_bot/logging/click_logger.py
crunchy_bot/logging/logger.py
crunchy_bot/logging/noop_logger.py
crunchy_bot/logging/test_click_logger.py
crunchy_bot/publisher/__init__.py
crunchy_bot/publisher/publisher.py
crunchy_bot/publisher/reddit_publisher.py
crunchy_bot/publisher/test_reddit_publisher.py
crunchy_bot-4.5.5.dist-info/LICENSE
crunchy_bot-4.5.5.dist-info/METADATA
crunchy_bot-4.5.5.dist-info/WHEEL
crunchy_bot-4.5.5.dist-info/entry_points.txt
crunchy_bot-4.5.5.dist-info/top_level.txt
crunchy_bot-4.5.5.dist-info/RECORD
