Metadata-Version: 2.1
Name: crunchy-bot
Version: 4.5.5
Summary: Crunchyroll Guest Pass Publisher for Reddit
Home-page: UNKNOWN
Author: David Lam
Author-email: david.lam@lamdav.com
License: MIT
Project-URL: Bug Reports, https://github.com/lamdaV/CrunchyBot/issues
Project-URL: Source, https://github.com/lamdaV/CrunchyBot
Platform: UNKNOWN
Classifier: Development Status :: 5 - Production/Stable
Classifier: Environment :: MacOS X
Classifier: Intended Audience :: End Users/Desktop
Classifier: License :: OSI Approved :: MIT License
Classifier: Programming Language :: Python :: 3.5
Classifier: Programming Language :: Python :: 3.6
Classifier: Programming Language :: Python :: 3.7
Classifier: Programming Language :: Python :: 3.8
Classifier: Topic :: Utilities
Requires-Python: >=3.5
Requires-Dist: Click (==7.1.1)
Requires-Dist: praw (==6.5.1)
Requires-Dist: prawcore (==1.0.1)
Requires-Dist: selenium (==3.141.0)
